{
  "GUZHENREN-KONG_QIAO1.title": "一转空窍",
  "GUZHENREN-KONG_QIAO1.description": "每场战斗，你打出的第1张低于[gold]一转[/gold]的蛊虫牌免费打出。\n战斗结束时，积累1/3/5（普通/精英/首领）点修为。\n还需[blue]{RemainingXp}[/blue]点修为突破。",
  "GUZHENREN-KONG_QIAO1.flavor": "一转蛊师空窍，产出青铜真元。",
  "GUZHENREN-KONG_QIAO2.title": "二转空窍",
  "GUZHENREN-KONG_QIAO2.description": "每场战斗，你打出的第1张低于[gold]二转[/gold]的蛊虫牌免费打出。\n战斗结束时，积累1/3/5（普通/精英/首领）点修为。\n还需[blue]{RemainingXp}[/blue]点修为突破。",
  "GUZHENREN-KONG_QIAO2.flavor": "二转蛊师空窍，产出赤铁真元。",
  "GUZHENREN-KONG_QIAO3.title": "三转空窍",
  "GUZHENREN-KONG_QIAO3.description": "每场战斗，你打出的第1张低于[gold]三转[/gold]的蛊虫牌免费打出。\n战斗结束时，积累1/3/5（普通/精英/首领）点修为。\n还需[blue]{RemainingXp}[/blue]点修为突破。",
  "GUZHENREN-KONG_QIAO3.flavor": "三转蛊师空窍，产出白银真元。",
  "GUZHENREN-KONG_QIAO4.title": "四转空窍",
  "GUZHENREN-KONG_QIAO4.description": "每场战斗，你打出的第1张低于[gold]四转[/gold]的蛊虫牌免费打出。\n战斗结束时，积累1/3/5（普通/精英/首领）点修为。\n还需[blue]{RemainingXp}[/blue]点修为突破。",
  "GUZHENREN-KONG_QIAO4.flavor": "四转蛊师空窍，产出黄金真元。",
  "GUZHENREN-KONG_QIAO5.title": "五转空窍",
  "GUZHENREN-KONG_QIAO5.description": "每场战斗，你打出的第1张低于[gold]五转[/gold]的蛊虫牌免费打出。\n战斗结束时，积累1/3/5（普通/精英/首领）点修为。\n还需[blue]{RemainingXp}[/blue]点修为突破。",
  "GUZHENREN-KONG_QIAO5.flavor": "五转蛊师空窍，产出紫晶真元。",
  "GUZHENREN-XIAN_QIAO6.title": "六转仙窍",
  "GUZHENREN-XIAN_QIAO6.description": "每场战斗，你打出的第1张低于[gold]六转[/gold]的蛊虫牌免费打出。\n战斗开始时，将1张[gold]青提仙元[/gold]加入手牌。\n还需[blue]{RemainingXp}[/blue]点修为突破。",
  "GUZHENREN-XIAN_QIAO6.flavor": "六转蛊仙仙窍，产出青提仙元。\n1～5转：免费打出第一章小于转数的牌，战斗结束时积累修为（普通/精英/首领：1/3/5）。\n6转以上产出仙元：6=青提、7=红枣、8=白荔、9=黄杏。",
  "GUZHENREN-XIAN_QIAO7.title": "七转仙窍",
  "GUZHENREN-XIAN_QIAO7.description": "每场战斗，你打出的第1张低于[gold]七转[/gold]的蛊虫牌免费打出。\n战斗开始时，将1张[gold]红枣仙元[/gold]加入手牌。\n还需[blue]{RemainingXp}[/blue]点修为突破。",
  "GUZHENREN-XIAN_QIAO7.flavor": "七转蛊仙仙窍，产出黄杏仙元。",
  "GUZHENREN-XIAN_QIAO8.title": "八转仙窍",
  "GUZHENREN-XIAN_QIAO8.description": "每场战斗，你打出的第1张低于[gold]八转[/gold]的蛊虫牌免费打出。\n战斗开始时，将1张[gold]白荔仙元[/gold]加入手牌。\n还需[blue]{RemainingXp}[/blue]点修为突破。",
  "GUZHENREN-XIAN_QIAO8.flavor": "八转蛊仙仙窍，产出白荔仙元。",
  "GUZHENREN-XIAN_QIAO9.title": "九转仙窍",
  "GUZHENREN-XIAN_QIAO9.description": "每场战斗，你打出的第1张低于[gold]九转[/gold]的蛊虫牌免费打出。\n战斗开始时，将1张[gold]黄杏仙元[/gold]加入手牌。",
  "GUZHENREN-XIAN_QIAO9.flavor": "世人谨记，我古月方源乃是大爱仙尊。"
}
